access_modifiers/__init__.py
access_modifiers/access_modifiers.py
access_modifiers/tests/__init__.py
access_modifiers/tests/test_performance.py
access_modifiers/tests/test_private.py
access_modifiers/tests/test_protected.py
access_modifiers-0.3.1.dist-info/LICENSE
access_modifiers-0.3.1.dist-info/METADATA
access_modifiers-0.3.1.dist-info/WHEEL
access_modifiers-0.3.1.dist-info/top_level.txt
access_modifiers-0.3.1.dist-info/RECORD
