Metadata-Version: 2.1
Name: access-modifiers
Version: 0.3.1
Summary: Private and protected access modifiers for Python
Home-page: https://github.com/fniessink/access-modifiers
Author: Frank Niessink
Author-email: frank@niessink.com
License: Apache 2.0
Keywords: access modifier,protected,private,oop
Platform: UNKNOWN
Classifier: Development Status :: 3 - Alpha
Classifier: Intended Audience :: Developers
Classifier: License :: OSI Approved :: Apache Software License
Classifier: Programming Language :: Python
Classifier: Programming Language :: Python :: 3 :: Only
Classifier: Programming Language :: Python :: 3.6
Classifier: Programming Language :: Python :: 3.7
Classifier: Topic :: Software Development
